[{"city":"测试","data":["测试"]},{"name":"淘宠·宠物店(新绿美地店)猫舍狗舍","phone":13197107464},{"name":"宠物店猫舍狗舍宠物基地","phone":13294283082},{"name":"同乐宠物馆(三和光谷道店)","phone":15107140503},{"name":"喵汪记宠物生活馆(佛奥·俊贤雅居店)","phone":15007112682},{"name":"购宠·布恩高端猫舍·宠物幼猫专售(汉街店)","phone":18711664585},{"name":"乐善宠物殡葬(发展大道店)","phone":15221871748},{"name":"伴侣宠物医疗(新华店)","phone":"15347117468;18602734648"},{"name":"温馨猫舍狗舍宠物基地(华润翡翠城1期店)","phone":13114490806},{"name":"汉尚嘉实多宠物店犬舍猫舍基地","phone":13294289772},{"name":"贝贝宠物乐园","phone":"027-83952542"},{"name":"吉利宠物-猫舍犬舍购宠基地(温馨苑A区店)","phone":13026170207},{"name":"陪它宠物生活馆·猫狗萌宠市场","phone":17724000019},{"name":"嘉实多宠物店猫舍狗舍基地","phone":13032777464},{"name":"皮班长宠物生活馆(坤合云海城店)","phone":18571505986},{"name":"乐善宠物殡葬·宠物火化善终服务(武昌店)","phone":15221871748},{"name":"萨德宠物","phone":18086161521},{"name":"可可宠物","phone":13177317097},{"name":"犬专科中心","phone":18971757176},{"name":"肖肖宠物","phone":13593705052},{"name":"宠爱宠物直营","phone":13872756727},{"name":"宜昌高新区欣旺犬舍","phone":"13997650252;13997657952"},{"name":"宠它王国","phone":13207225191},{"name":"禧它宠物医疗中心","phone":19071724471},{"name":"爱莱宠物(江天一色中央内街)","phone":15872460594},{"name":"臻宠宠物馆(语港旺府店)","phone":19108691572},{"name":"萌宠之家宠物店","phone":18727015833},{"name":"多肉格宠物店","phone":15271009990},{"name":"这是一家宠物店","phone":17607110070},{"name":"爱心宠物救助","phone":13635795369},{"name":"宠尚宠物会馆","phone":18671104989},{"name":"收猫狗","phone":13597984158},{"name":"多贝宠物","phone":17386463063},{"name":"维特宠物医疗中心","phone":13581354266},{"name":"萌宠来了","phone":13797992696},{"name":"燕子宠物(保丽国际广场店)","phone":13971335949},{"name":"卡多宠物","phone":13487192778},{"name":"联合宠物医疗中心","phone":18271755295},{"name":"宠物兵团","phone":"13707128381;15971229333"},{"name":"星佐伊宠物诊疗中心","phone":19986793130},{"name":"格伦宠物","phone":15027045182},{"name":"爱宠情缘","phone":"13986652399;15347245277"},{"name":"米米呀猫舍","phone":13027107950},{"name":"慈护宠物店","phone":18907216008},{"name":"希望宠物之家","phone":15072838361},{"name":"爱尚宠物萌宠宠物生活馆","phone":13409889271},{"name":"活羊活狗专卖","phone":"13409991662;13477616600"},{"name":"多多宠物店","phone":13409676676},{"name":"博爱宠物","phone":13409869138},{"name":"宠爱有家","phone":15872791118},{"name":"宠爱宠物美容会所","phone":15207245040},{"name":"柚嘉猫舍东观路店","phone":18727934559},{"name":"爱尚宠屋生活馆(齐星花园店)","phone":18372200717},{"name":"博爱宠物医疗","phone":"15072976117;15897652388"},{"name":"贝贝宠物诊所","phone":"13277224286;18971798683"},{"name":"0宠宠物会所","phone":18727755522},{"name":"修猫修狗宠物店","phone":15957610548},{"name":"修猫修狗小动物维修中心","phone":15347029620},{"name":"鹤峰宠物店","phone":"13124433666;13517182518"},{"name":"伊加一宠物自助洗浴","phone":19008662591},{"name":"南湖宠物狗市场","phone":18908453469},{"name":"宠物基地长沙猫舍犬舍宠物市场","phone":13294289772},{"name":"食嘢猫屋猫咖猫舍(五一新干线店)","phone":18692215988},{"name":"瑞派宠物医院24小时急诊犬猫诊疗中心(松雅店)","phone":17375778855},{"name":"长沙华景猫舍犬舍大型宠物市场","phone":18170035243},{"name":"湘上嘟嘟猫舍狗舍宠物市场","phone":13114490806},{"name":"猫隐间·猫咖","phone":"15115335935;18169252040"},{"name":"南湖宠物基地","phone":"18711861646;19374880088"},{"name":"正欣铭宠(犬舍猫舍宠物基地)","phone":15212062917},{"name":"白沙犬舍猫舍犬猫繁殖基地宠物狗场狗舍宠物市场(中海国际社区四期店)","phone":18874250503},{"name":"长沙九星宠物猫舍犬舍宠物市场(新南天·古汉国际广场4幢店)","phone":15381567386},{"name":"长沙大型猫舍犬舍宠物市场","phone":13584984541},{"name":"购宠·长沙精品猫舍·幼猫专售宠物店","phone":19573688960},{"name":"拜迪宠物医院(南城首府店)","phone":18807421563},{"name":"贝贝康宠物超市","phone":13975106269},{"name":"湘尚宠物基地猫舍犬舍","phone":18696017413},{"name":"拜迪宠物(萌宠直售店)","phone":18807421563},{"name":"精工精心宠物服务中心猫舍狗舍(相遇商业广场店)","phone":18071385414},{"name":"长沙关于·它·宠物猫狗大型基地","phone":15798499863},{"name":"树岛宠物生活馆","phone":19898892422},{"name":"巴布先生长沙大型宠物市场猫舍犬舍宠物店","phone":19558208096},{"name":"超级橘子皮宠物超市","phone":13548717092},{"name":"小熊宠物(景致雅苑店)","phone":19151990520},{"name":"108宠物","phone":17608400022},{"name":"长沙肥猫·宠物·猫舍犬舍大型宠物市场","phone":15798499863},{"name":"HI baby宠物社","phone":"13308432398;17775738515"},{"name":"喜多宠物","phone":18670750994},{"name":"爱摩仕宠物会所·猫狗活体专售","phone":13281119040},{"name":"奈斯宠物生活馆","phone":"15575831933;17352860606"},{"name":"宠浪(碧桂园·玖玺台店)","phone":19158355545},{"name":"奈斯宠物医疗中心","phone":"0731-23280668"},{"name":"奈斯宠物生活馆","phone":13762256423},{"name":"贵族宠物","phone":13908430743},{"name":"活羊活狗零售批发","phone":13873385835},{"name":"维恩宠物","phone":18670901242},{"name":"希望宠物龙泊湾分店","phone":15907324936},{"name":"宠生宠物生活服务馆","phone":15200505241},{"name":"浩峰宠物托运","phone":"13907472822;17397342102"},{"name":"尾巴生活宠物馆","phone":18216047231},{"name":"俩王一炸宠物零食仓储折扣店","phone":15074750829},{"name":"喜多宠物","phone":18229278865},{"name":"布丁宠物","phone":19176786958},{"name":"金格林宠物生活馆","phone":13618444889},{"name":"宠物美容","phone":18620391787},{"name":"星辰阳光犬舍","phone":17673916061},{"name":"奈斯宠物","phone":"13544790816;15364495546"},{"name":"宠爱有家","phone":17700570887},{"name":"奥德彪宠物超市","phone":"15068227161;16600280520"},{"name":"优宠宠物领养馆(岳阳总店)","phone":"0730-8180991"},{"name":"佳贝宠爱宠物连锁(清哥说猫)","phone":13100207654},{"name":"岳阳心忆宠物生命纪念馆宠物善终服务","phone":17769308619},{"name":"狗德猫宁宠物店","phone":"15576101781;18574910821"},{"name":"宠易宠物乐园","phone":13337360770},{"name":"宠物医疗会所","phone":13787877156},{"name":"康达宠物店","phone":13873755212},{"name":"悉心宠物店","phone":18673744054},{"name":"道格宠物乐园","phone":17347250702},{"name":"皇家宠物会所","phone":15115534273},{"name":"波波宠物会所","phone":15111618297},{"name":"萌宠能量站","phone":17674657729},{"name":"奈斯宠物","phone":15274648742},{"name":"巴雷宠物会所","phone":18075787159},{"name":"萌哆哆(新天地店)","phone":18174516666},{"name":"萌哆哆宠物店(锦绣五溪店)","phone":19145956780},{"name":"居居宠物","phone":19974513960},{"name":"溆浦宠悦汇宠物工作室","phone":"15111526398;18244834051"},{"name":"多多宠物店","phone":15674054753},{"name":"保罗犬舍","phone":18244873228},{"name":"木木宠物会所","phone":15197818666},{"name":"私宠宠物会所","phone":13873814979},{"name":"狗友故事宠物","phone":18574332770},{"name":"奇趣宠物","phone":13974386253},{"name":"萌狗乐园","phone":18229501819},{"name":"爱狗狗宠物护理中心","phone":15174334567},{"name":"广州珍宠狗场犬舍猫舍宠物市场基地","phone":13678903415},{"name":"谷的猫宁猫咖领养馆","phone":15043729993},{"name":"喵汪公社宠物店","phone":"13798023894;13828482034"},{"name":"Trendy Cattery潮猫舍宠物店","phone":"13424148794;18675036213"},{"name":"俏美丽小暴龙宠物店","phone":19313702001},{"name":"哆乐天小小宠物店","phone":18696017413},{"name":"特哆哆宠物店猫舍狗舍宠物基地","phone":13294289772},{"name":"王小乖宠物馆(智库.布拉诺创意小镇店)","phone":18372556760},{"name":"邻小虎宠物用品猫舍犬舍宠物市场(大石店)","phone":13071283976},{"name":"TIANPET天宠中国·宠物火化善终(广州旗舰店)","phone":"020-39909099;18818805101"},{"name":"邻小虎宠物用品猫舍犬舍宠物市场(市桥店)","phone":13071283976},{"name":"邻小虎宠物用品猫舍犬舍宠物市场(江南西店)","phone":13071283976},{"name":"小暴龙宠物猫舍狗舍基地(汇侨新城南区店)","phone":13047183173},{"name":"邻小虎宠物用品猫舍犬舍宠物市场(同和店)","phone":13071283976},{"name":"邻小虎宠物用品猫舍犬舍宠物市场(客村店)","phone":13071283976},{"name":"乐善宠物善终服务中心(天河黄村一分店)","phone":13533624488},{"name":"邻小虎宠物用品猫舍犬舍宠物市场(陈家祠店)","phone":13071283976},{"name":"邻小虎宠物用品快送超市(员村店)","phone":13071283976},{"name":"壹加宠物猫舍狗舍基地(万科里购物中心店)","phone":13047183173},{"name":"eredo宠物猫舍狗舍活体市场","phone":16753843650},{"name":"乐善宠物殡葬·宠物火化善终服务(海珠前进店)","phone":13533624488},{"name":"广州白云太和宠物小屋(太和金铂天地店)","phone":15889938885},{"name":"伊斯登公寓","phone":15918445587},{"name":"龙族宠物店犬舍猫舍宠物基地(万俪购物中心店)","phone":13618619935},{"name":"喵吉·猫屋·猫舍","phone":19128012514},{"name":"我的猫·猫舍·猫咪生活馆(百年东街店)","phone":19925012514},{"name":"多里九金宠物用品工厂店","phone":13192888862},{"name":"窝窝萌宠森友会","phone":13316990571},{"name":"得宠宠物医院","phone":18588987532},{"name":"米乐乖乖宠物生活馆(后海总店)","phone":13316840322},{"name":"街边的猫(流浪猫领养站)","phone":13113859078},{"name":"瑞鹏宠物深圳第一中心医院","phone":"0755-26088366;18903026990"},{"name":"龙兴猫之家","phone":13760474047},{"name":"萌比宠物基地","phone":15077725475},{"name":"亮亮猫舍","phone":13360064471},{"name":"漫宠宠物·猫咪·金丝熊·荷兰猪·龙猫(西丽店)","phone":13712035631},{"name":"君萌宠物(只售卖狗狗)(南山店)","phone":17303776016},{"name":"旺喵宠物基地宠物市场犬舍猫舍狗场繁殖基地","phone":19166265224},{"name":"足迹宠物销售中心(海逸雅居店)","phone":18802683044},{"name":"懒猫宠物(梅林店)","phone":17722571330},{"name":"XINGPET星宠·宠物善终殡葬火化(深圳湾旗舰店)","phone":17675401269},{"name":"深圳好韵宠物店猫舍狗舍宠物基地","phone":15572592897},{"name":"足迹宠物销售中心(龙岗中心城店)","phone":15915491841},{"name":"随心精品猫舍·宠物猫(罗湖店)","phone":18785651446},{"name":"懒猫宠物(清湖店)","phone":17722571330},{"name":"意生宠物-留仙洞店","phone":19924685055},{"name":"懒猫宠物(东门天地店)","phone":17704089298},{"name":"宠物心语诊疗中心(石龙仔店)","phone":18038048070},{"name":"深圳萌宠宠物猫舍犬舍宠物基地(碧湖玫瑰园店)","phone":18579111719},{"name":"懒猫宠物(龙岗店)","phone":17704089298},{"name":"启萌宠物(天琴阁店)","phone":13316517370},{"name":"新医佳宠物医院·骨外科·牙专科","phone":15622851710},{"name":"懒猫宠物(南油店)","phone":17704089298},{"name":"随心精品猫舍·宠物猫(西乡店)","phone":18929320337},{"name":"邻小虎宠物用品猫舍犬舍宠物市场(田贝店)","phone":13071283976},{"name":"宠宠宠物市场宠物店宠物犬舍猫舍狗场(富洲商务店)","phone":19128461083},{"name":"邻小虎宠物用品猫舍犬舍宠物市场(沙井店)","phone":13071283976},{"name":"龙华好韵宠物店超大型基地猫狗售卖","phone":16753843650},{"name":"这里有猫咪·猫舍·宠物店(光明店)","phone":18028780274},{"name":"港岛宠物猫狗基地馆(汇龙苑店)","phone":13675261377},{"name":"邻小虎宠物用品猫舍犬舍宠物市场(龙华店)","phone":13071283976},{"name":"喵酱宠物店","phone":15302762673},{"name":"深圳猫舍犬舍宠物基地宠物店","phone":13759971653},{"name":"粤上猫咪领养宠物店猫舍基地市场","phone":13237296908},{"name":"宠物店超大型猫舍狗舍基地","phone":17687624502},{"name":"汪小艾宠物生活馆(深圳湾店)","phone":"13714426496;17324459330"},{"name":"深圳好韵宠物店大型基地猫舍犬舍","phone":19071241864},{"name":"邻小虎宠物用品猫舍犬舍宠物市场(横岗店)","phone":13071283976},{"name":"晴天宠物(桐林城市广场店)","phone":"13538259254;18200983194"},{"name":"邻小虎宠物用品猫舍犬舍宠物基地(西丽店)","phone":13071283976},{"name":"拾忆空间·宠物火化殡葬善终服务(南头店)","phone":19066359501},{"name":"多多宠物","phone":13168050468},{"name":"暖暖宠物度假山谷","phone":"13727885860;15018347186"},{"name":"珠海猫舍犬舍宠物基地","phone":17328388265},{"name":"珠海猫舍犬舍宠物基地狗场","phone":13022861807},{"name":"珠海猫舍犬舍宠物基地宠物店","phone":13519125978},{"name":"珠海金宠宠物批发市场正规犬舍猫舍宠物基地","phone":13192213139},{"name":"榄溪沙萌宠乐园","phone":13680399418},{"name":"名宠优选(兰埔店)","phone":13085825300},{"name":"富贵喵猫咖宠物店","phone":15113147167},{"name":"拉菲猫舍","phone":13232528618},{"name":"糖宠sugar pet(珠海最大犬舍)","phone":18926903890},{"name":"艾米莉的宠物乐园","phone":18128130676},{"name":"哈比宠物","phone":13075637629},{"name":"港澳宠物托运","phone":13005778802},{"name":"洛斯宠物","phone":13340859260},{"name":"汕头喵利莱宠物猫舍(市场店)","phone":13715852957},{"name":"萌宠犬舍猫舍宠物市场猫狗基地(购宠中心)","phone":17136678953},{"name":"宠此嘉景宠物店","phone":"13556498758;17376635324"},{"name":"希诺宠物","phone":13825847708},{"name":"哈尼宠物","phone":"13433362626;15113060767"},{"name":"南澳爱宠店","phone":13413433580},{"name":"麦高宠物","phone":13085751851},{"name":"宠遇店铺","phone":13318051507},{"name":"引宠入室","phone":"13433374501;15816774502"},{"name":"威玛特世界名犬舍猫舍狗场","phone":"15766995599;15766996669"},{"name":"小叮铛宠物店·宠物猫舍犬舍宠物猫咪洗澡","phone":18024193409},{"name":"四季宠物医院","phone":16789344599},{"name":"佛山奕奕犬舍狗场宠物基地","phone":"13660094800;13826230631"},{"name":"天佑宠火化善终服务","phone":18024112895},{"name":"奇喵屋猫舍(万科金域中央32座店)","phone":18125255747},{"name":"广东宠物庄园·犬舍猫舍宠物乐园(万达广场店)","phone":18520955161},{"name":"兜友猫狗宠物·养殖基地","phone":"13535535501;13536636051;15800080160"},{"name":"牧和邻·猫舍狗舍·宠物基地","phone":13114490806},{"name":"乐善宠物服务部(狮山店)","phone":13533624488},{"name":"萌宠犬舍猫舍宠物市场猫狗购宠基地","phone":13690517095},{"name":"柴之护宠物佛山柴犬舍","phone":18520959559},{"name":"美思世界名犬猫舍狗场(创产店)","phone":13068662505},{"name":"老兵CFA宠物猫舍","phone":13570001239},{"name":"江门宠物喵狗基地宠物店","phone":13048153779},{"name":"江门宠物基地猫舍犬舍宠物店","phone":13022861807},{"name":"江门宠物基地新会萌宠乐园宠物庄园","phone":13726197619},{"name":"江门宠物狗售卖总部犬舍狗舍狗场宠物店","phone":13670334137},{"name":"圣格宠物店","phone":"0750-5588483"},{"name":"爱犬舍宠物","phone":18026811317},{"name":"永久犬舍","phone":13676168289},{"name":"狗士多","phone":13760510799},{"name":"百佳宠物","phone":13560505099},{"name":"萌萌宠物生活会馆(湛江店)","phone":13106618708},{"name":"宝国宠物店","phone":13600377334},{"name":"阿龙白切狗批发零售","phone":13189480000},{"name":"多乐宠物寄养","phone":13414979243},{"name":"茂名大白名宠宠物店","phone":15218350104},{"name":"哆咪宠物.寄养洗护(时尚名居店)","phone":18000918197},{"name":"贝勒宠宠","phone":18476565210},{"name":"诺德宠物医疗中心","phone":19927071961},{"name":"萌猫宠物用品","phone":15875836844},{"name":"名宠宠物会馆","phone":"15946167345;16646598080"},{"name":"杰瑞宠物店","phone":13845153036},{"name":"伊贝宠宠物会馆","phone":13009929593},{"name":"宠萌鸟店","phone":13244675888},{"name":"哈基咪宠物会馆","phone":18804555575},{"name":"才貌双犬·幼犬基地·宠物狗·繁殖犬舍·买狗宠物店","phone":13611971791},{"name":"宠颜宠物猫狗售卖旗舰店","phone":13764522452},{"name":"上海D幢宠物基地犬舍猫舍市场","phone":15629413112},{"name":"佰家宠宠物旗舰店","phone":17623389558},{"name":"吾家宠物医院·24小时·宠物绝育","phone":18116491817},{"name":"Paw DAY宠物旗舰店","phone":13661449468},{"name":"顺强宠物诊所(嘉定店)","phone":18121093975},{"name":"浦东宠物猫狗基地市场犬舍猫狗(阳光城·愉景公馆店)","phone":19071242454},{"name":"斑马叔叔宠物店(季乐路店)","phone":13818463440},{"name":"上海宠物基地宠物店猫舍狗舍","phone":18571968730},{"name":"喵喵优品宠物店","phone":13524637958},{"name":"顺心宠物诊所(东汉阳路店)","phone":13524784350},{"name":"赛派·宠物美容猫狗专卖旗舰店(美康路店)","phone":15921131720},{"name":"爱嘉宠物店(精品猫狗售卖)","phone":15618251858},{"name":"松江区多多宠物乐园市场","phone":18872693031},{"name":"小佩宠物(森林湾家园店)","phone":18018524486},{"name":"宠物店在这里猫舍狗舍基地","phone":13093202715},{"name":"名猫屋宠物店","phone":13301750373},{"name":"spring wild萨摩耶主题狗咖·猫咖(贸易中心店)","phone":18205087835},{"name":"江宁名宠基地.犬舍猫舍(秦淮总店)","phone":13141650021},{"name":"高端萌宠","phone":15921339150},{"name":"艾贝尔宠物24H医院·心脏科·外科(仙林湖店)","phone":"025-52620151"},{"name":"大橘家(猫咪生活馆)","phone":18014490617},{"name":"欣宠猫屋(观城南楼店)","phone":15312044200},{"name":"光光宠物基地猫舍犬舍(浦口店)","phone":13913822449},{"name":"南京大型猫狗宠物市场基地(猫狗繁育)","phone":13003650329},{"name":"艾贝尔宠物24H医院·眼科转诊(鼎新路店)","phone":"025-84839292"},{"name":"南京金宠宠物市场犬舍猫舍狗舍狗场购宠基地","phone":18994099314},{"name":"梦宠山庄·宠物专售·犬猫专售(南京总店)","phone":13327807913},{"name":"赫本宠物(保利·罗兰香谷店)","phone":"18205509585;18362965248"},{"name":"南京大型宠物市场猫狗市场猫舍犬舍高端萌宠","phone":15317608578},{"name":"莱乐宠物医院·24H夜诊·眼科·微创中心(江宁店)","phone":"025-87175219;18051015233"},{"name":"宫之宠·名宠基地(南京总店)","phone":15817336332},{"name":"就是宠.猫舍犬舍宠物基地","phone":13301594818},{"name":"梦宠山庄·宠物专售·犬猫专售(江宁店)","phone":13327807913},{"name":"南京大型宠物基地犬舍猫舍","phone":19071242454},{"name":"宠物批发零售犬舍猫舍基地狗舍","phone":19313702001},{"name":"梦宠山庄·宠物专售·犬猫专售(鼓楼店)","phone":13327807913},{"name":"南京精品猫舍·幼猫专售宠物店(新街口店)","phone":17368488260},{"name":"南京宠物直销基地大型猫舍犬舍","phone":19103029774},{"name":"南京宠物基地猫舍犬舍宠物市场","phone":15658837991},{"name":"欣乐意宠物店犬舍猫舍宠物基地","phone":15629413112},{"name":"狗德猫宁-宠物市场(玄武)","phone":18344654448},{"name":"暖洋宠物诊疗中心(弘阳时光里二期店)","phone":18021402998},{"name":"橙果班班宠物店","phone":18761600744},{"name":"小岛生活馆宠物基地宠物店宠物市场","phone":19256847237},{"name":"讨喜宠物·精品猫舍犬舍预约店","phone":19256847237},{"name":"TIANPET天宠中国·宠物火化善终(南京店)","phone":18061650010},{"name":"米可南京大型宠物市场批发猫舍犬舍宠物基地","phone":19256847237},{"name":"鹿鹿宠物·精品犬猫专卖","phone":18795851051},{"name":"洁宠宠物服务中心南京旗舰店","phone":"17368681590;17766071590"},{"name":"宠物港·宠物基地","phone":19313702001},{"name":"叮噹宠物(亚都天元大厦A座店)","phone":13093202715},{"name":"友家南京大型宠物批发市场猫舍犬舍宠物基地","phone":19256847237},{"name":"小龙吖宠物用品超市","phone":"13851236050;19516901748;19805040222"},{"name":"森森尼卡萌宠森林","phone":18068307986},{"name":"苏锡名宠基地","phone":18101522570},{"name":"梦宠山庄·实体连锁·幼犬专售·无锡犬舍(无锡总店)","phone":15695222908},{"name":"领者宠物宠物店犬舍猫舍基地市场","phone":13047183173},{"name":"无锡宠爱有它宠物市场猫舍犬舍宠物基地","phone":13072538731},{"name":"宠物店猫舍犬舍基地宠物市场","phone":19071241864},{"name":"小精灵宠物·宠物基地","phone":15807265081},{"name":"森凌宠物·猫舍狗舍·宠物基地","phone":19071242454},{"name":"汪思宠宠物诊所免疫点骨科影像异宠","phone":"13915372577;18168377121"},{"name":"汉尚领者宠物店犬舍猫舍","phone":15799314058},{"name":"聚宠财宠物生活馆(花样年花郡家园店)","phone":18014957002},{"name":"领者宠物猫舍狗舍基地(孔雀雅园1期店)","phone":19807242460},{"name":"基地沪上领者宠物狗场猫舍","phone":17720552903},{"name":"吉宠宠物生活馆(长泰店)","phone":15961806781},{"name":"DC宠物·猫舍狗舍·宠物基地","phone":13114490806},{"name":"无锡猫太郎宠物店猫舍犬舍宠物基地","phone":13732999541},{"name":"艾米丽宠物美容店","phone":18961750861},{"name":"吾舍领猫馆滨湖店","phone":17318809981},{"name":"宠物店","phone":"13641668707;18762639913"},{"name":"江阴宠物基地(猫舍狗舍.猫狗专卖)","phone":18261551315},{"name":"狗班长宠物空间(宠小格品牌合作店)","phone":17860862123},{"name":"萌喜宠物(天虹·世纪城店)","phone":15949000303},{"name":"拉斯阿拉一家宠物店","phone":13605211273},{"name":"米苏宠物","phone":18051353672},{"name":"大圣宠物用品","phone":18021838890},{"name":"派哒哒宠物用品店","phone":17606199472},{"name":"存爱宠物","phone":18852298885},{"name":"大圣宠物用品批发商贸","phone":18021838890},{"name":"宠物店","phone":15380177238},{"name":"大陆宠物生活馆","phone":18121787157},{"name":"维尼宠物","phone":15852374089},{"name":"凯撒宠物会所","phone":13063540588},{"name":"宠米粒宠物生活馆","phone":19295266394},{"name":"宠米粒宠物店猫舍犬舍宠物基地","phone":18696017413},{"name":"旺财当家宠物活体·猫舍犬舍(新城南都花海店)","phone":"17315125909;17315125936"},{"name":"宠物犬舍猫舍活体直销","phone":13685235872},{"name":"常宠名宠·大型犬舍猫舍基地·宠物猫狗活体","phone":18118003059},{"name":"有你宠物·猫舍狗舍·宠物基地","phone":15017144871},{"name":"常宠天下·大型购猫中心·宠物猫狗活体","phone":18118003059},{"name":"纳尔宠物犬舍活体直销","phone":19858362225},{"name":"宠米粒宠物·活体直营店","phone":17606013884},{"name":"龙猫生活馆(兔子仓鼠金丝熊)","phone":13057198333},{"name":"逗萌·猫舍狗舍·宠物基地","phone":18501711710},{"name":"多多宠物(城中花苑店)","phone":13685251518},{"name":"卿卿佰宠·宠物生活馆","phone":13347899112},{"name":"咪果宠物","phone":18051819135},{"name":"米格犬舍猫舍宠物店","phone":13216100621},{"name":"本森宠物沙龙","phone":"0519-83381199"},{"name":"哈基米宠物店","phone":15995075069},{"name":"宠乐缘宠物店","phone":18861133777},{"name":"卡尔宠物生活馆","phone":"0519-89197378"},{"name":"昆山阳光大型宠物市场犬舍猫舍基地","phone":13170875592},{"name":"苏州大型宠物基地猫狗宠物市场","phone":13073667935},{"name":"苏州香山犬业","phone":"18115500869;18951100869"},{"name":"姑苏名宠基地.犬舍猫舍购宠中心","phone":18550472537},{"name":"苏宠家·大型猫狗市场宠物基地(猫狗专卖)","phone":17521027749},{"name":"极星宠物医院(木渎店)","phone":18326809655},{"name":"猫狗贸易公司宠物店犬舍猫舍基地市场","phone":13047183173},{"name":"宫之宠·宠物基地(苏州总店)","phone":13771827019},{"name":"梦宠山庄·实体连锁·幼犬专售·苏州犬舍(苏州总店)","phone":18051822127},{"name":"(盛泽)萌宠猫狗基地","phone":13912733996},{"name":"苏州宠物基地大型猫狗宠物市场·犬舍猫舍","phone":18926405564},{"name":"超级狗宠物中心(太湖中路店)","phone":"13851494889;18662169888"},{"name":"辛巴宠物(超华城市广场店)","phone":"18118421169;19962188959"},{"name":"万福家猫舍宠物旗舰店","phone":15599054220},{"name":"苏州宠物基地(盛泽大旺宠物)","phone":13912733996},{"name":"益泰宠物(花海家园店)","phone":18551019665},{"name":"宠辉宠物医疗(九溪墅店)","phone":18051869168},{"name":"宠辉宠物医疗(暨阳东路店)","phone":"0512-58660969"},{"name":"苏州宠物批发零售基地(猫狗宠物市场)","phone":13116737294},{"name":"姑苏区宠小宝宠物基地猫舍狗舍宠物市场(喜临门商业广场店)","phone":13177158073},{"name":"派多格宠物(花集路店)","phone":18062784343},{"name":"七宝宠物店","phone":18601433335},{"name":"小贝宠物店","phone":13806134909},{"name":"派多格宠物(昆山吾悦商场店)","phone":18936110340},{"name":"朋友の狗狗宠物店","phone":"13962417827;18206222728"},{"name":"苏尚阿里斯顿宠物店猫舍犬舍宠物基地","phone":17720552903},{"name":"初见宠物生活馆(蔚蓝四季花园西区店)","phone":18020230407},{"name":"猫狗日记宠物店宠物基地猫舍犬舍","phone":19376658130},{"name":"汪喵宠物馆(原泓森新湖明珠城聆湖苑店)","phone":15706215742},{"name":"沪上阿里斯顿宠物店猫舍犬舍","phone":19313702001},{"name":"柒柒宠物店","phone":18601433335},{"name":"伊宠宠物犬舍猫舍宠物市场(昆山店)","phone":13067741557},{"name":"哈奇宠物店","phone":13771836207},{"name":"大通名宠基地犬舍猫舍","phone":18018423137},{"name":"南通三只猫宠物·超大繁育基地·精品宠物猫舍","phone":18022461395},{"name":"西米宠物","phone":18994226712},{"name":"私宠精选宠物基地猫舍犬舍","phone":18672439401},{"name":"安娜宠物(皮毛调理紫琅店)","phone":18751314500},{"name":"爱宠生活会所(金鼎名城鼎寓店)","phone":"15862779841;18306279565"},{"name":"BEST PET丨倍宠宠物(万象店)","phone":"0513-51000566;18112222322"},{"name":"MMC领猫馆(南通中南店)","phone":18962888417},{"name":"东升训犬","phone":15252636355},{"name":"爱尚宠物店","phone":15862714036},{"name":"米米宠物生活馆","phone":18706295915},{"name":"贴心宠物","phone":18888050333},{"name":"索尔宠物","phone":18151329050},{"name":"仙狗私宠馆","phone":19516936988},{"name":"贝塔宠物","phone":13270407570},{"name":"迪莫宠物","phone":15251240766},{"name":"佩奇宠物店","phone":15195712345},{"name":"洛洛爱宠","phone":18795550737},{"name":"多多乐宠","phone":15751237206},{"name":"艾米宠物店","phone":"15996123630;18651253881"},{"name":"三宝宠物","phone":13775590557},{"name":"永康宠物生活馆","phone":"13401263072;13775411066"},{"name":"麦克宠物","phone":15251256349},{"name":"贝贝宠物","phone":"13815633585;15961315231"},{"name":"三宝宠物","phone":13645130697},{"name":"圣杰宠物","phone":18551888300},{"name":"派多格宠物","phone":17206038663},{"name":"猫姐姐宠物生活馆","phone":15152410026},{"name":"茉莉宠屋","phone":13395211341},{"name":"贝贝宠物用品总汇","phone":15051398895},{"name":"布布宠物店","phone":"13182913739;18752350378"},{"name":"莱恩宠物","phone":15050804620},{"name":"优咪·You Mi(WCF猫舍)","phone":15921154635},{"name":"相遇宠物生活馆(新城花园B区店)","phone":18261282465},{"name":"八一晨晨宠物医院","phone":"13645112057;13645113337"},{"name":"小米宠物店","phone":18068881298},{"name":"琳琳的宠物店","phone":15051083785},{"name":"汉堡家宠物店","phone":13901416082},{"name":"宠物店","phone":13236131452},{"name":"森森水族森森新零售体验店","phone":"13813424852;18601501020"},{"name":"卡卡宠物店","phone":13914631918},{"name":"贝爱佳萌宠生活馆","phone":17551754290},{"name":"润生小宠当家(清华园店)","phone":15251002308},{"name":"777宠物会所(曲江店)","phone":"18796607520;18796666686"},{"name":"洛洛宠屋","phone":"19952455623;19952456665"},{"name":"多多宠物店","phone":18061154899},{"name":"贝拉宠物","phone":"0514-89993361"},{"name":"四爪兽宠物医疗","phone":18796622159},{"name":"阿猫阿狗宠物店","phone":18036231432},{"name":"肉肉宠物诊所","phone":18852589107},{"name":"潘多拉宠物医院美容院","phone":"13952899291;15205289618"},{"name":"文格艾斯宠物会所","phone":18921567970},{"name":"洛萨宠物","phone":18115149454},{"name":"艾塔宠物店","phone":15952950221},{"name":"圣宠宠物(靖江德诚店)","phone":18351145456},{"name":"凯利蓝宠物","phone":13852637119},{"name":"巴迪宠物会所","phone":13951162335},{"name":"博爱宠物","phone":15261010898},{"name":"贝贝宠物生活馆","phone":"13961007201;18652668782"},{"name":"沃夫宠物","phone":15695231102},{"name":"维特宠物医疗","phone":"15195229689;17851351269"},{"name":"亿只宠萌宠生活馆","phone":"0523-86553778;13092259618;17705269618"},{"name":"这里有家宠物店","phone":18360072906},{"name":"贝贝宠物店","phone":18351061772},{"name":"汤姆宠物","phone":"13511775399;18451845133"},{"name":"宠物店","phone":14762627363},{"name":"西西宠物店","phone":15161267218},{"name":"五月宠物","phone":18017550925},{"name":"奥斯卡宠物美容","phone":19852793513},{"name":"万贯宠物用品店","phone":18360140130},{"name":"杭州宠物市场猫狗市场(宠物批发零售)","phone":17395717917},{"name":"杭州猫舍犬舍大型宠物市场(批发零售)","phone":15921339150},{"name":"点点宠物店·猫狗售卖(塘萍路店)","phone":13336131762},{"name":"杭州尚城宠物基地大型宠物市场(批发零售)","phone":18662513116},{"name":"杭州猫狗宠物基地宠物市场","phone":15317608578},{"name":"杭州宠物市场(官方认证)·卖狗·宠物出售·韩系比熊","phone":18158112863},{"name":"宫之宠·宠物犬舍猫舍(杭州上城店)","phone":13051110681},{"name":"杭宠家大型宠物市场猫狗宠物基地","phone":15921339150},{"name":"杭州宠物基地猫舍犬舍宠物市场","phone":15170479053},{"name":"赤松子宠物诊所(杭州中大银泰百货店)","phone":"0571-87169619;19357105296"},{"name":"一诺宠物医院阿里总院旗舰店","phone":18106583500},{"name":"杭宠派·大型猫狗市场宠物基地(猫狗专卖)","phone":17521027749},{"name":"杭州大型宠物猫狗市场售卖基地萌轩宠物店(杭州总部)","phone":13326139313},{"name":"杭州临平宠物店猫舍犬舍宠物基地","phone":15070966690},{"name":"楠木宠物基地宠物市场宠物店(杭州总部)","phone":13326139313},{"name":"杭州酷宠猫舍犬舍大型宠物市场","phone":15350004528},{"name":"杭州西文猫舍犬舍宠物市场","phone":18170035243},{"name":"杭州有家宠屋大型宠物市场猫舍犬舍宠物店","phone":15005596172},{"name":"杭州德胜猫舍犬舍大型宠物基地市场","phone":17607918651},{"name":"初见宠物馆(好望角公寓店)","phone":18969082256},{"name":"杭州大型宠物基地(滨江店)","phone":19807242460},{"name":"杭州犬舍猫舍宠物市场猫狗宠物基地杭宠家","phone":15317608578},{"name":"杭尚宠星球宠物店猫舍犬舍基地","phone":13237296908},{"name":"摩卡宠物生活馆(江南摩卡店)","phone":15868400133},{"name":"觅遇宠物猫舍狗舍基地(万科·草庄东岸店)","phone":18071385414},{"name":"爱它宠物火化殡葬善终(金都·雅苑店)","phone":18005719117},{"name":"二胖家宠物店","phone":17107766898},{"name":"欢喜宠物(高运锦园店)","phone":18268169251},{"name":"荡秋千的猫猫舍狗舍宠物基地(联合世纪新筑店)","phone":13264951867},{"name":"毛团宠物店","phone":19357558351},{"name":"精灵宠物托运(风雅乐府店)","phone":13221068339},{"name":"杭州大型宠物基地(猫狗批发市场)","phone":15658837991},{"name":"宠事利宠物(自由城润景店)","phone":13282136616},{"name":"伊宠宠物基地·犬舍狗舍活体宠物狗市场萌宠直销","phone":19357583886},{"name":"尚城宠物基地(杭州猫狗市场批发)","phone":15558098159},{"name":"杭州万合宠物猫舍狗舍宠物市场","phone":15629413112},{"name":"舒克和贝塔宠物店","phone":13388609820},{"name":"宁波宠物犬舍猫舍狗场狗市宠物店宠物市场养殖基地(批发零售)","phone":17867969447},{"name":"慈溪宠物市场","phone":13586785567},{"name":"宁波宠物市场犬舍猫舍狗场养殖基地","phone":15658280102},{"name":"宁波海曙江北鄞州宠物批发领养中心","phone":13586785567},{"name":"宁波宠物批发","phone":13586563745},{"name":"宁波兄弟宠物托运寄养","phone":"13429243268;13777133700"},{"name":"宁波市余姚慈溪绍兴宠物市场狗狗批发","phone":15258292650},{"name":"甬宠名宠基地犬舍猫舍活体直营","phone":18069110432},{"name":"宁波市慈溪余姚低塘宠物市场狗狗繁殖基地","phone":15924390349},{"name":"猫肥狗旺宠物生活馆(富达广场C区店)","phone":18357460409},{"name":"原宠.高端猫舍.猫咪售卖(天一店)","phone":"15301915136;17706482339"},{"name":"尊宠宠物犬舍猫舍幼宠基地(维科·馨院西区店)","phone":18067291352},{"name":"韩韩家宠物店·高端私宠·美容洗护","phone":13082956885},{"name":"胖胖的猫-宠物猫舍(长丰店)","phone":18605116667},{"name":"宠爱e森犬舍猫舍宁波宠物市场宠物基地","phone":15058205458},{"name":"喵喵狗宠物","phone":13123896378},{"name":"宠爱尼名宠·狗舍猫舍·宠物基地","phone":19313702001},{"name":"宠爱尼名宠猫舍犬舍宠物基地","phone":18696017413},{"name":"好汉的宠物店猫舍犬舍宠物基地","phone":17687624502},{"name":"宠爱·猫舍狗舍·宠物基地","phone":13294283082},{"name":"西米宠物","phone":18768565941},{"name":"小开开の宠物店","phone":15825580316},{"name":"宠此无忧宠物大药房(万达店)","phone":17758230108},{"name":"心意宠物馆(演武花园店)","phone":19519209953},{"name":"甜宝宠物(新华园西区店)","phone":18669490919},{"name":"慈溪狗王宠物","phone":13586552568},{"name":"道格小屋宠物生活馆","phone":15058822607},{"name":"宁波猫舍犬舍宠物基地狗场","phone":17328388265},{"name":"糖喵喵宠物","phone":13738824948},{"name":"宁波蓝谛宠物店","phone":17306380095},{"name":"犬舍猫舍店·宠物基地·猫舍狗舍","phone":17764100774},{"name":"薄荷叶宠物生活馆","phone":15005596172},{"name":"大鹏宠物店","phone":18005239919},{"name":"艾尚宠物馆","phone":"14705740547;15958842055"},{"name":"琼瑶宠物店","phone":13065697736},{"name":"瓯宠名宠基地-高端猫狗活体直营(站前东小区店)","phone":18868251077},{"name":"肉肉宠物生活馆·宠物医院·急重症(印象汇店)","phone":18157735577},{"name":"可欣家庭小猫舍","phone":13032721888},{"name":"诚之萌宠物店宠物基地宠物市场猫舍犬舍直销","phone":17858848213},{"name":"麦乐斯宠物·猫舍狗舍·宠物基地","phone":15807265081},{"name":"旺旺犬舍","phone":"13356125589;13721180101"},{"name":"温尚宠爱尼名宠物猫舍狗舍基地","phone":15572592897},{"name":"宠爱尼名宠猫舍犬舍基地","phone":17720552903},{"name":"有间猫舍宠物","phone":13738315513},{"name":"温州喜乐宠物托运","phone":13091929956},{"name":"严佳训犬寄养","phone":13117830370},{"name":"安妮宠物生活馆","phone":"15888268295;18268999949"},{"name":"辉大大宠物生活馆","phone":13091992351},{"name":"豆丁萌宠宠物店","phone":15267765116},{"name":"悠米宠物","phone":17858050306},{"name":"这是一家宠物店","phone":15158457037},{"name":"猫狗联盟宠物市场-猫舍犬舍宠物店宠物基地","phone":15005596172},{"name":"汪汪宠物猫舍犬舍宠物市场","phone":13246677842},{"name":"嘉兴猫舍犬舍宠物基地宠物店","phone":13227732027},{"name":"嘉兴市猫狗宠物基地联盟","phone":17505734727},{"name":"贝尔康宠物医疗部","phone":15372329770},{"name":"爱乐猫舍犬舍","phone":13362321152},{"name":"爱宝宠物(犬猫销售宠物洗护美容)","phone":13282331118},{"name":"我有猫(紫元尚园店)","phone":"0573-82807785;13221327701"},{"name":"桐乡全职狗妈萌宠","phone":18257366622},{"name":"胖仙女猫舍(城南路店)","phone":13252307581},{"name":"一家宠物(禾兴南路店)","phone":13965276151},{"name":"恋宠宠物会所","phone":18268388868},{"name":"麦德姆宠物","phone":13586319360},{"name":"小马宠物店","phone":18957305553},{"name":"小胖妞宠物(中利达花园西区店)","phone":19883827831},{"name":"湖州小怪兽宠物基地猫舍犬舍宠物店","phone":18192856326},{"name":"呼呼虎宠物店","phone":13857273321},{"name":"多米宠物料理","phone":18767281796},{"name":"7仔宠物(织里店)","phone":"17706822920;18767279501"},{"name":"奈斯宠物生活馆","phone":15868253067},{"name":"小米宠物会所","phone":15268707525},{"name":"宠爱有家","phone":"15088370176;15088730176"},{"name":"宠物大当家","phone":"18257285013;18257385013"},{"name":"绍兴越城柯桥宠物猫狗批发领养中心","phone":13586785567},{"name":"海明犬舍狗舍宠物市场基地","phone":13777323603},{"name":"绍兴萌宠犬舍猫舍购宠基地宠物市场","phone":15715851288},{"name":"韵之家宠屋","phone":"18367578764;18758508952"},{"name":"海威犬舍狗舍宠物市场基地","phone":13586675843},{"name":"Good咪咪·猫舍","phone":13588460975},{"name":"盟趣宠物店(官河横路店)","phone":15888063162},{"name":"选宠基地·宠物认养犬舍猫舍·宠物市场","phone":18175978538},{"name":"喜猫生活馆","phone":18058661664},{"name":"小七动物诊疗(铂金商贸大厦店)","phone":13867551622},{"name":"招财宠物市场犬舍狗舍猫舍狗场购宠基地","phone":13723319774},{"name":"猫大仙猫舍","phone":18367566760},{"name":"哆哆宠物店","phone":18458520350},{"name":"洛克宠物生活馆","phone":18857500629},{"name":"维特宠物用品","phone":13004611932},{"name":"娜娜猫舍","phone":15958566447},{"name":"义乌新军宠物托运","phone":18767991999},{"name":"义乌旺族宠物店大型购宠犬舍猫舍","phone":19376658908},{"name":"大脸宠物医疗","phone":17336768938},{"name":"宠铺宠物猫舍犬舍宠物销售基地","phone":"13355555673;18557905490"},{"name":"金华沁诚宠物屋猫舍犬舍宠物基地","phone":14796568256},{"name":"义乌大型购宠猫舍犬舍选宠基地柳韵宠物","phone":14745471190},{"name":"合鑫宠物基地(幼猫幼狗专卖)","phone":14796568256},{"name":"义乌十月宠物馆猫舍犬舍宠物基地","phone":18720938280},{"name":"贝贝宠物出售猫舍犬舍大型购宠基地","phone":17857950999},{"name":"佳雯宠物中心医院·骨科·心肺·牙科(盛世天成店)","phone":18167029782},{"name":"毅家宠物(三店)","phone":18857941777},{"name":"友间宠物","phone":13738949899},{"name":"奥奥宠物乐园(活体猫狗专卖)","phone":15669615692},{"name":"安骑机车club宠物店犬舍宠物基地猫舍市场","phone":15629413112},{"name":"鼎瑞宠物幼猫幼犬活体售卖","phone":19918922547},{"name":"Aebi Pet爱彼宠物(绿城兰园·兰馨苑店)","phone":17131193333},{"name":"杰杰宠物乐园(萌宠猫狗专卖)","phone":"17757941649;13586965343"},{"name":"卡卡宠物会所(屋基村店)","phone":"13566710943;13566971070"},{"name":"义乌宠屿猫狗双全犬舍猫舍宠物基地","phone":"13255892788;13735651920"},{"name":"元气萌宠猫舍犬舍宠物基地","phone":15825795903},{"name":"宠一点宠物店","phone":13735551645},{"name":"青然宠物(万达店)","phone":"0579-82821838;13221275696;18042577969"},{"name":"义乌沐铭大型基地购宠选宠猫舍犬舍大型宠物店","phone":15367845358},{"name":"青澜宠物(金义新区店)","phone":"0579-82707116;13221275696"},{"name":"芒果宠物出售基地","phone":19534208886},{"name":"青然宠物人民东路店","phone":"0579-82285385;15067592839"},{"name":"梨法宠物(和悦邻里中心店)","phone":"15355388100;17816421116"},{"name":"亮亮宠物(金华义乌市)","phone":"13058973727;13732415161"},{"name":"喜萌宠物","phone":18067656270},{"name":"爱宠家壹号院店","phone":"13291580280;18157957833"},{"name":"宠一点宠物店","phone":13221260560},{"name":"萌友宠物生活馆","phone":"18736730813;18989412568"},{"name":"贝尚宠物馆","phone":15345799973},{"name":"可可宠物","phone":18767994284},{"name":"安家宠物猫舍犬舍宠物基地二店","phone":14796842035},{"name":"泰胜宠物店猫舍犬舍","phone":14745471190},{"name":"狗德猫宁·猫舍狗舍·宠物基地","phone":18008691205},{"name":"漫漫宠物生活馆","phone":18367989230},{"name":"十二家宠屋","phone":17274321235},{"name":"萌友宠物生活馆","phone":18946416341},{"name":"新语宠物诊疗中心","phone":17280954360},{"name":"小麦芽萌宠(后宅杜元店)","phone":17761676866},{"name":"小费宠物店","phone":18957945831},{"name":"大米宠物店","phone":"13566793520;15355377567"},{"name":"萌宠太医院·24小时动物急重症转诊中心(横店总店)","phone":"19906579239;19941278756"},{"name":"有间鸟舍","phone":15167956996},{"name":"TaTa它它宠物银桂小区店","phone":18857019114},{"name":"衢州墩墩宠物市场·韩版比熊·全犬种","phone":15068967773},{"name":"衢州市宠物市场","phone":13326103308},{"name":"初心宠物(绿江南店)","phone":15968844687},{"name":"宠儿宠物会所","phone":18268961259},{"name":"宠爱有家","phone":15857052413},{"name":"安泰宠物诊所","phone":15857080137},{"name":"澡澡宠物医院临城总院","phone":13018813237},{"name":"毛毛宠物·大型购宠基地(舟山平价猫舍)","phone":17606806326},{"name":"台州宠物犬舍猫舍狗场狗市宠物市场宠物养殖基地","phone":18358660821},{"name":"喵心犬舍宠物市场猫舍狗场宠物基地","phone":18358660821},{"name":"P&P LAND宠物生活馆","phone":15906867749},{"name":"美宠纪","phone":18989652266},{"name":"阿猫阿狗宠物店","phone":13282687697},{"name":"薏米宠物生活馆(华景店)","phone":15868627610},{"name":"兴旺犬舍猫舍宠物市场狗场狗市宠物养殖基地","phone":18358660821},{"name":"一伴宠物","phone":17671390674},{"name":"徐汪汪训犬学院(台州椒江店)","phone":13957658265},{"name":"向日葵宠物商店","phone":15958699843},{"name":"台州欧耶萌宠物店犬舍猫舍","phone":17770095653},{"name":"喵喵屋猫舍-蓝金渐层·拿破仑矮脚(颐景名苑店)","phone":15167675809},{"name":"金绿缘训犬学校","phone":"15957616588;16565655678"},{"name":"铲屎官宠物店","phone":13454642000},{"name":"它爱宠物","phone":13806570153},{"name":"宠乐缘宠物店","phone":13456615865},{"name":"小马家宠物生活馆","phone":15858696088},{"name":"宠爱有家","phone":13819646022},{"name":"佩奇宠物生活馆","phone":15867672005},{"name":"爱狗宠物会所","phone":"13058625668;18006869949;18776568888"},{"name":"亿只宠萌宠生活馆","phone":15967281681},{"name":"吉吉宠屋生活馆","phone":13615788855},{"name":"这是一家宠物店","phone":18857800847},{"name":"米奇宠物","phone":15967287851},{"name":"和印富丽图文缙云紫薇北路店","phone":13735972947},{"name":"合肥萌宠大型宠物市场基地犬舍猫舍","phone":18178917093},{"name":"梦宠山庄·宠物专售·犬猫专售(合肥总店)","phone":18582888860},{"name":"萌宠宠园.犬舍猫舍·猫狗专卖·宠物出售","phone":"13625633128;15856972356"},{"name":"铲屎官宠物乐园(萌宠猫狗专卖)","phone":18356007970},{"name":"集宠+人宠交互空间(合肥新粮仓旗舰店)","phone":18156513365},{"name":"庐阳区爱心宠物猫狗市场","phone":18872693031},{"name":"胖乎乎宠物·萌宠专卖","phone":19315238286},{"name":"小松犬舍猫舍·猫狗专卖宠物店·购宠基地市场","phone":"13625633128;15856972356"},{"name":"梦宠山庄·宠物专售·犬猫专售(包河店)","phone":18582888860},{"name":"梦宠山庄·宠物专售·犬猫专售(新站店)","phone":18582888860},{"name":"可糖宠物·萌宠售卖·洗护美容(融创壹号院)","phone":17333060703},{"name":"宠里萌宠专售(文锦新城店)","phone":"15155976322;17775373212"},{"name":"康派尼宠物医院","phone":"13295609281;15926533074"},{"name":"杰睿犬舍猫舍基地卖猫卖狗宠物售卖","phone":"13625633128;15856972356"},{"name":"哈娜家宠物生活馆","phone":"15255464671;15255464673"},{"name":"哆啦·宠物基地·猫舍狗舍","phone":13114490806},{"name":"舜发宠物·繁育基地·猫舍狗舍·宠物基地","phone":17764100774},{"name":"喵见宠物(万达广场店)","phone":"17356530517;18949848960"},{"name":"龙猫树异宠·猫舍(十六年老店)","phone":"0551-62626977;15305603977"},{"name":"老万博·猫舍狗舍·宠物基地","phone":19071242454},{"name":"合肥鸢时宠物店","phone":"13275697922;18856042353"},{"name":"壹品宠汇宠物生活馆","phone":18756110997},{"name":"花花宠物(龙誉城店)","phone":18756901635},{"name":"特麦萌宠物·猫舍犬舍宠物基地","phone":"15629413112;15586173129"},{"name":"爱宠屋·猫咖(北门店)","phone":15905651234},{"name":"合庐阳二人萌宠宠物基地猫舍狗舍","phone":13294283082},{"name":"乌托邦猫咖·撸猫·游戏·售猫(三里庵店)","phone":15609683795},{"name":"小淘气宠物(绿地海德公馆店)","phone":15305690853},{"name":"卡皮巴拉宠物生活馆","phone":18655308848},{"name":"汉堡家宠物生活馆","phone":"18861500775;19856881365"},{"name":"佩奇宠物生活馆","phone":"18324715157;18715089427"},{"name":"皮皮宠物","phone":13505618354},{"name":"薄荷糖羊驼萌宠奶茶店","phone":15005532477},{"name":"汪呜宠物馆","phone":17718273690},{"name":"宝宝贝贝宠物生活馆(阳光花园B区店)","phone":"13705539993;13966016288"},{"name":"爱尚宠物店","phone":15155355999},{"name":"仁民宠物会所","phone":15255342029},{"name":"叮当萌宠(宠物殡葬)","phone":15505530553},{"name":"万泽宠物店","phone":18155312411},{"name":"宠爱有家","phone":18255210322},{"name":"多多宠物美容培训学校","phone":18715182226},{"name":"阿龙宠物店","phone":18555520313},{"name":"宠乐缘宠物店","phone":15955273161},{"name":"中央广场淘气宠物店","phone":18555025162},{"name":"阿玛宠物俱乐部","phone":13155258848},{"name":"约克夏之家宠物店","phone":18096550663},{"name":"爱尚宠物店","phone":18895607990},{"name":"山野拾趣","phone":17309640875},{"name":"宠爱有家","phone":19156151451},{"name":"爱宠(西城河店)","phone":"13905548878;17355491116"},{"name":"西施宠物","phone":13966482191},{"name":"夸克宠物会所","phone":13695611644},{"name":"宠颐生宠物医院·异宠科·骨外科·犬猫全科转诊中心(朝辉首府店)","phone":"0555-8335885;19955569400"},{"name":"AMC宠物医院·内窥镜·微创骨外科诊疗中心(马鞍山花山店)","phone":"0555-2340755"},{"name":"安妮宠物","phone":18298236216},{"name":"龙猫宠物","phone":15258855962},{"name":"心级宠屋","phone":18325588071},{"name":"五月宠物服务中心","phone":17355519599},{"name":"宠物美容","phone":18055515509},{"name":"黑色优宠宠物美容培训(湖畔御景店)","phone":15040475373},{"name":"宠客宠物生活馆宠物寄养酒店","phone":18856100600},{"name":"卡其宠物店","phone":15756089581},{"name":"希望之秋宠物店","phone":13261188282},{"name":"爪哇岛宠物生活馆","phone":13966133212},{"name":"富贵宠物用品店","phone":13381032029},{"name":"娜娜宠物","phone":19905625776},{"name":"宠颐生宠物医院·骨外科·微创·犬猫全科诊疗中心(安庆总院)","phone":"0556-5557088"},{"name":"不二家の宠物(猫狗批发)","phone":15555669167},{"name":"莱斯宠物","phone":"13355566258;13966926823"},{"name":"七宝萌宠乐园","phone":15919758883},{"name":"多乐宠物","phone":15155980781},{"name":"安妮宠物美容","phone":18755986847},{"name":"萌宠大作战","phone":18297692706},{"name":"Pet·宠物(碧桂园·名邸店)","phone":18075251715},{"name":"大芳宠物店","phone":18355010132},{"name":"宠爱有家","phone":13637007220},{"name":"苏滁毛孩子宠物店","phone":15156557573},{"name":"米奇喵喵屋宠物乐园(临泉县土地管理局家属院店)","phone":15856794256},{"name":"西米宠物服务中心","phone":15255853044},{"name":"自由宠宠物工作室","phone":"13564793515;15240090305"},{"name":"喵肥狗壮宠物生活馆(黄金时代西清苑店)","phone":19118418630},{"name":"曼利宠物店","phone":"17775009077;18356625922"},{"name":"宠物美疗","phone":"15067204100;15067250287"},{"name":"宠物之家","phone":17682880886},{"name":"宠物幼园","phone":18158930909},{"name":"大波宠物","phone":15357873799},{"name":"爱犬俱乐中心","phone":13655584498},{"name":"宠物美疗","phone":13965576606},{"name":"格林宠物","phone":"15910357499;19333215060"},{"name":"友家宠物","phone":18755837260},{"name":"奈斯宠物生活馆","phone":18895452224},{"name":"爱狗宠物会馆","phone":13345577778},{"name":"通达宠物托运","phone":15855727960},{"name":"宠爱有家","phone":18298076100},{"name":"莱卡犬舍","phone":18155727298},{"name":"六安霍山萌堡宠物基地","phone":18715644555},{"name":"塔塔屋宠物店","phone":18297885483},{"name":"独山宠物店","phone":18056488301},{"name":"南河福龙湾兔喜生活","phone":"13225840913;18094255227"},{"name":"阿里旺旺宠物生活馆","phone":18156439202},{"name":"贝塔格儿童摄影会馆(新都会环球广场店)","phone":"0564-3353939"},{"name":"遥远宠物店批发狗粮猫粮","phone":"18133306136;18133306138"},{"name":"铲屎官宠物店","phone":13156732909},{"name":"精灵宠物会所","phone":18056836970},{"name":"无敌宠物","phone":15055078571},{"name":"艾米的宠物店","phone":17356797767},{"name":"奥贝力狼宠物食品经销处","phone":"13705672162;13856738062"},{"name":"宠物医院洗澡用品","phone":17855653333},{"name":"宠颐生宠物医院·骨外科·犬猫全科诊疗中心(池州店)","phone":"0566-2621742"},{"name":"友家宠物","phone":13215669884},{"name":"道格宠物用品批发","phone":"13156666601;13856666006"},{"name":"波波宠物","phone":"13866956001;13866956475"},{"name":"安康宠物会所","phone":15056347840},{"name":"小佩宠物(金山大道店)","phone":15980207093},{"name":"福旺财连锁宠物专卖店","phone":18060509991},{"name":"购宠·福州精品猫舍犬舍·猫狗专售宠物店(富力中心店)","phone":13075880009},{"name":"旺旺乐园宠物批发(福州店)","phone":18450240297},{"name":"禧牧宠物·伊珊娜授权店","phone":"13675089890;18695617120"},{"name":"阿翔宠物猫狗专卖","phone":17850867668},{"name":"半闲猫咖","phone":18259000384},{"name":"友家宠物","phone":19959112395},{"name":"三只喵犬舍猫舍宠物基地","phone":18170014048},{"name":"福哆啦·猫舍狗舍·宠物基地","phone":17764100774},{"name":"它可宠物(金山公园店)","phone":18559127256},{"name":"福宠·猫狗专卖(福州总店)","phone":18559941889},{"name":"猫肥狗壮·猫狗专卖(南台十六府店)","phone":13960891838},{"name":"瑞辰动物缘宠物医院·猫科·异宠(台江宝龙分院)","phone":"0591-88381818;18900276866"},{"name":"它可宠物(仓山万达店)","phone":18960896187},{"name":"小柒萌宠(猫粮·猫砂·狗粮)","phone":18050331559},{"name":"它可宠物(东二环泰禾店)","phone":18559863896},{"name":"尼莫宠物","phone":18060361581},{"name":"瑞派宠物·猫科·犬猫外科·中兽医科·老年保健科(吕厝分院)","phone":"0592-5326733"},{"name":"海迪岸水族馆","phone":"0592-5514095;18059830088"},{"name":"阿古朵宠物(禾祥西店)","phone":18559253656},{"name":"SHOW PET宠物店","phone":13720878848},{"name":"心悦宠物店","phone":19120666499},{"name":"厦门吉利宠物店猫舍犬舍","phone":17770095653},{"name":"厦门恩善宠物殡葬(24h火化)","phone":19896610135},{"name":"圣宠宠物(国贸商城·同悦店)","phone":18205927429},{"name":"西西宠物美容","phone":17605056617},{"name":"熊岛宠物生活","phone":13716272775},{"name":"宠爱有家","phone":15860707250},{"name":"可吉斯宠物(保利·叁仟栋壹海里店)","phone":18850034611},{"name":"立立宠物(鸿发苑店)","phone":13306054125},{"name":"狗老大宠物会所(东圳店)","phone":13286978888},{"name":"旺旺乐园宠物批发(莆田店)","phone":"18650496694;18705091900"},{"name":"奇奇宠物黄石店","phone":"15992557816;17859324771"},{"name":"汤姆宠物店","phone":18959524567},{"name":"猫与狗宠物生活馆","phone":13107999012},{"name":"奇奇宠物","phone":13960253606},{"name":"肖肖水族","phone":15625197118},{"name":"爱尚宠家宠物诊所","phone":15880890559},{"name":"晋江宠物批发","phone":17880352951},{"name":"小宠乐园宠物店(宠物批发)","phone":15260497669},{"name":"泉州喵屋猫咪寄养酒店","phone":18065558788},{"name":"安心宠物店","phone":13799450461},{"name":"御和宠·顽宠世家宠物医院(濠江店)","phone":15750931777},{"name":"泉州宠物批发(总店)","phone":"17349584045;18065750501"},{"name":"帕恰宠物基地猫舍犬舍","phone":13072538731},{"name":"泉州艾咪宠物活体专卖","phone":15270859974},{"name":"泉州万达宠物批发","phone":"17349584045;18065750501"},{"name":"泉州超爱宠物店犬舍猫舍","phone":19170037630},{"name":"笨丫丫萌宠(金利花苑小区店)","phone":15160321833},{"name":"陈氏宠物","phone":"0595-87654222;15375878222;18960306893"},{"name":"皮皮宠物","phone":15880757700},{"name":"牧牧宠屋","phone":15985903733},{"name":"比特斯宠物北石分店","phone":18150978398},{"name":"瑞宠宠物医疗·石狮宠物批发","phone":18105957222},{"name":"康贝宠物医院腾飞店","phone":"0596-2053701;15059652001"},{"name":"乐宠·宠物(猫狗批发万达店)","phone":17744065315},{"name":"皮班长宠物连锁超市(北京路店)","phone":"13599688877;17350279177"},{"name":"尤展宠物(旧镇店)","phone":17396534349},{"name":"楠楠宠物店","phone":19859253938},{"name":"宠爱有家","phone":13306061115},{"name":"八月宠物工作室","phone":13205967660},{"name":"赖皮蛇水族","phone":18760383096},{"name":"萌团宠物犬舍猫舍宠物基地","phone":4008835012},{"name":"宠物之家","phone":"17705997598;18305027161"},{"name":"乐宠宠物","phone":"14759953829;19005090996"},{"name":"佩塔宠物","phone":18859065236},{"name":"南巷猫舍宠物店","phone":15280655012},{"name":"佩塔小家宠物店","phone":"15059262751;18750307324"},{"name":"东区水族宠物店","phone":"13101470727;15659969237"},{"name":"猫店·猫咖猫舍","phone":"13667916531;15270985831"},{"name":"萌俏欢狗狗犬舍猫舍活体批发基地宠物店","phone":18579163627},{"name":"私房小宠猫舍犬舍活体批发宠物店","phone":15070950777},{"name":"南昌无双宠物店犬舍猫舍宠物市场","phone":15270907677},{"name":"南昌精品猫狗专售店猫舍犬舍宠物店","phone":15679136587},{"name":"狗狗塘(精品宠物专卖)犬舍猫舍","phone":18942231783},{"name":"懒猫宠物店犬舍猫舍宠物市场","phone":15679136587},{"name":"南昌游毅犬舍猫舍宠物市场","phone":15679136587},{"name":"朋来缘犬猫宠物基地(洪铃大厦店)","phone":18907089773},{"name":"南昌喵心犬意宠物猫狗活体直销宠物店","phone":17370053819},{"name":"猫狗俱乐部.精品猫狗专卖店.托运.寄养","phone":13177870721},{"name":"麦斯萌宠(猫狗专卖店)","phone":17053742930},{"name":"犬舍宠物狗场猫舍宠物市场购宠基地","phone":17770857733},{"name":"TOGO宠物铜锣湾店·犬舍猫舍·活体宠物销售","phone":13617000360},{"name":"多来米宠物猫狗活体专售犬舍直销(联泰香域尚城店)","phone":"13117818587;19100192548"},{"name":"e家宠物售卖寄养托远(理想家园·泉水湾店)","phone":13767495585},{"name":"101康贝宠物诊疗中心","phone":"0791-85083101;17807918101"},{"name":"精品宠物批发零售(十里·水岸桃花店)","phone":15180478198},{"name":"宠物都市(象湖店)","phone":15079121692},{"name":"作兴嫩宠物基地猫舍犬舍宠物市场","phone":13065125969},{"name":"南昌喵爪爪宠物猫舍犬舍购宠(中央香榭店)","phone":15079152127},{"name":"爱宠驿站宠无优(猫咪专售)","phone":"15156281701;18970803170"},{"name":"南昌宠物基地猫舍犬舍","phone":18629268171},{"name":"宠物庄园宠物狗宠物猫","phone":15979048211},{"name":"南昌心艺宠物美容店","phone":18807912191},{"name":"有家宠物(九颂山河店)","phone":13361658142},{"name":"喜莱宠物·精品萌宠专卖","phone":17770855507},{"name":"提莫猫屋","phone":17679110608},{"name":"萌俏欢狗狗犬舍猫咪批发基地宠物店(红谷滩店)","phone":15579132613},{"name":"汪汪萌宠宠物店猫舍犬舍活体批发","phone":13065125969},{"name":"邻小虎宠物用品猫粮猫砂狗粮快送超市西湖店","phone":19318565191},{"name":"爱宠时代宠物美容生活馆","phone":13970893212},{"name":"MameShiba院子(豆柴犬舍)","phone":19170096029},{"name":"熊熊狗狗猫咪领养(万达广场店)","phone":13330107168},{"name":"小v萌宠","phone":15797906507},{"name":"东东宠物店","phone":"13735781927;18457550636"},{"name":"旺喵宠物店活体批发零售犬舍猫舍","phone":17379813883},{"name":"可可宠物","phone":"13907891774;13907981774"},{"name":"九江君鹏宠物托运(诚信小区店)","phone":15297925352},{"name":"开心萌宠宠物","phone":15279257094},{"name":"喜樂宠物(九悦庭店)","phone":13133660051},{"name":"哈宝的宠物店","phone":13177735257},{"name":"喜樂宠物·喜樂猫咖(快乐城店)","phone":13133661159},{"name":"诺琴宠物基地大型犬舍批发基地","phone":17307927934},{"name":"D.C宠物生活馆(名猫名犬专营)","phone":18460005630},{"name":"PET.HOME.宠物名猫名犬出售","phone":"18870080439;19914566236"},{"name":"萌猫当家宠物店","phone":15720983988},{"name":"Colacat宠物生活馆","phone":17779227722},{"name":"筱佳人宠物店","phone":"17679226285;17770849934"},{"name":"诺琴宠物生活馆(信华城市花园店)","phone":"15397817735;17770047744;19065755571"},{"name":"宠物之家","phone":13755220899},{"name":"派斯宠物","phone":15658332722},{"name":"贝贝宠物店","phone":13113654227},{"name":"乔乔宠物店","phone":15070274320},{"name":"爱诺宠物繁殖基地","phone":13662245565},{"name":"何氏宠物医疗中心","phone":"0790-6206556;13755705739"},{"name":"森里宠物寄养中心","phone":18207908822},{"name":"哈基咪宠物","phone":18807013989},{"name":"萌宠宠物·宠物售卖(万象城总店)","phone":"18172797144;19142190525"},{"name":"邻家爱宠·宠物店","phone":15507082025},{"name":"乐宠宠物(黄金花园东区店)","phone":15297889768},{"name":"皮皮宠物中心","phone":"18682231682;19144494663"},{"name":"帕克宠物生活馆","phone":13097179687},{"name":"云梦宠物店","phone":15679717919},{"name":"卡卡宠物生活馆","phone":13317085152},{"name":"宠必备宠物药房","phone":16679071453},{"name":"贝贝宠物","phone":15297975013},{"name":"三宝宠物医疗诊所","phone":18170799686},{"name":"宠物医疗预防","phone":"13870702464;15070717907"},{"name":"宠物美容用品批发","phone":13763960513},{"name":"花里森活猫咖馆(滨江3期店)","phone":18807966764},{"name":"多多宠屋","phone":16750145015},{"name":"艾洛摄影工作室","phone":18979686080},{"name":"派多格宠物用品店(猫狗售卖)","phone":15970277880},{"name":"天使宠物(五洲花园店)","phone":15909458919},{"name":"米奇喵汪屋","phone":18279546592},{"name":"皮克喵宠物生活馆","phone":17679017993},{"name":"熊宠宠物","phone":18707040749},{"name":"赫拉宠物","phone":15679492503}]